{
  "step": 3600,
  "generations": {
    "s_named_girl": [
      {
        "seed": 0,
        "tokens": [
          20037,
          13,
          1375,
          6151,
          284,
          711,
          287,
          262,
          3952,
          351,
          607,
          2460,
          13,
          1881,
          1110,
          11,
          20037,
          2497,
          607,
          1545,
          5045,
          1820,
          290,
          4966,
          284,
          1265,
          683,
          329,
          617,
          34397,
          13,
          5045,
          1820,
          338,
          1995,
          531,
          11,
          366,
          19457,
          11,
          475,
          307,
          8161,
          407,
          284,
          4483,
          1997,
          13,
          632,
          338,
          7786,
          526,
          198,
          198,
          43,
          813,
          1422,
          470,
          588,
          262
        ],
        "text": "Once upon a time, there was a little girl named Lily. She loved to play in the park with her friends. One day, Lily saw her friend Timmy and ran to ask him for some carrots. Timmy's mom said, \"Sure, but be careful not to eat anything. It's sharp.\"\n\nLily didn't like the"
      },
      {
        "seed": 1,
        "tokens": [
          20037,
          13,
          1375,
          6151,
          284,
          3551,
          319,
          607,
          1995,
          338,
          3072,
          13,
          1881,
          1110,
          11,
          20037,
          338,
          1995,
          1965,
          607,
          284,
          1037,
          651,
          617,
          14746,
          13,
          20037,
          373,
          6568,
          284,
          1037,
          11,
          475,
          607,
          1995,
          531,
          340,
          373,
          1165,
          2739,
          13,
          198,
          198,
          43,
          813,
          338,
          1995,
          1422,
          470,
          1577,
          510,
          13,
          1375,
          655,
          1965,
          607,
          9955,
          611,
          339,
          373
        ],
        "text": "Once upon a time, there was a little girl named Lily. She loved to write on her mom's phone. One day, Lily's mom asked her to help get some cookies. Lily was excited to help, but her mom said it was too late.\n\nLily's mom didn't give up. She just asked her dad if he was"
      },
      {
        "seed": 2,
        "tokens": [
          20037,
          13,
          1881,
          1110,
          11,
          673,
          1816,
          284,
          262,
          3952,
          351,
          607,
          1995,
          1820,
          13,
          1375,
          2497,
          257,
          2933,
          508,
          3114,
          6507,
          13,
          1375,
          1965,
          683,
          644,
          373,
          2642,
          13,
          198,
          198,
          464,
          2933,
          531,
          11,
          366,
          40,
          460,
          470,
          1064,
          1997,
          326,
          3073,
          588,
          526,
          198,
          198,
          43,
          813,
          338,
          1310,
          2933,
          338,
          1995,
          1820,
          1392,
          281,
          2126,
          13
        ],
        "text": "Once upon a time, there was a little girl named Lily. One day, she went to the park with her mommy. She saw a boy who looked sad. She asked him what was wrong.\n\nThe boy said, \"I can't find anything that looks like.\"\n\nLily's little boy's mommy got an idea."
      },
      {
        "seed": 3,
        "tokens": [
          20037,
          13,
          1375,
          6151,
          284,
          711,
          2354,
          290,
          2298,
          12734,
          13,
          1881,
          1110,
          11,
          673,
          2497,
          257,
          35113,
          287,
          262,
          11376,
          13,
          20037,
          373,
          12008,
          284,
          1949,
          284,
          4929,
          340,
          11,
          475,
          607,
          1995,
          1820,
          1297,
          607,
          284,
          307,
          8161,
          290,
          307,
          8161,
          13,
          198,
          198,
          43,
          813,
          373,
          845,
          8161,
          290,
          1422,
          470,
          1309,
          262,
          35113,
          6129,
          1497,
          13
        ],
        "text": "Once upon a time, there was a little girl named Lily. She loved to play outside and pick flowers. One day, she saw a butterfly in the garden. Lily was scared to try to catch it, but her mommy told her to be careful and be careful.\n\nLily was very careful and didn't let the butterfly fly away."
      },
      {
        "seed": 4,
        "tokens": [
          20037,
          13,
          1375,
          6151,
          284,
          711,
          2354,
          287,
          262,
          6290,
          290,
          4391,
          287,
          279,
          4185,
          829,
          13,
          1881,
          1110,
          11,
          20037,
          338,
          1995,
          1820,
          2921,
          607,
          257,
          1263,
          16225,
          290,
          484,
          2826,
          351,
          262,
          6290,
          13,
          220,
          198,
          198,
          43,
          813,
          373,
          523,
          3772,
          290,
          2921,
          607,
          1995,
          1820,
          257,
          1263,
          16225,
          13,
          1375,
          6151,
          607,
          1995,
          1820,
          523,
          881
        ],
        "text": "Once upon a time, there was a little girl named Lily. She loved to play outside in the rain and jump in puddles. One day, Lily's mommy gave her a big hug and they played with the rain. \n\nLily was so happy and gave her mommy a big hug. She loved her mommy so much"
      }
    ],
    "s_scared": [
      {
        "seed": 0,
        "tokens": [
          673,
          8288,
          284,
          711,
          351,
          607,
          14958,
          13,
          1375,
          3114,
          1088,
          262,
          2119,
          290,
          2497,
          257,
          1263,
          256,
          21874,
          6842,
          319,
          262,
          18316,
          13,
          1375,
          2227,
          284,
          4273,
          340,
          290,
          307,
          663,
          1545,
          13,
          1375,
          6807,
          284,
          262,
          269,
          4185,
          306,
          290,
          12615,
          607,
          11880,
          13,
          632,
          2936,
          2705,
          290,
          2705,
          13,
          1375,
          2936,
          257,
          1310,
          4378,
          1359,
          607,
          9686
        ],
        "text": "Lily was scared because she liked to play with her toys. She looked around the room and saw a big teddy bear on the shelf. She wanted to pet it and be its friend. She walked to the cuddly and touched her tongue. It felt soft and soft. She felt a little tickling her nose"
      },
      {
        "seed": 1,
        "tokens": [
          673,
          1422,
          470,
          760,
          703,
          284,
          1057,
          13,
          887,
          607,
          1995,
          1820,
          2497,
          607,
          290,
          531,
          11,
          366,
          16454,
          11,
          20037,
          13,
          3914,
          338,
          467,
          1561,
          284,
          607,
          290,
          1560,
          607,
          546,
          607,
          9707,
          526,
          220,
          198,
          198,
          43,
          813,
          531,
          11,
          366,
          2504,
          338,
          8788,
          11,
          20037,
          13,
          3914,
          338,
          467,
          1561,
          546,
          20037,
          290,
          766,
          607,
          14532,
          526
        ],
        "text": "Lily was scared because she didn't know how to run. But her mommy saw her and said, \"Okay, Lily. Let's go talk to her and tell her about her joke.\" \n\nLily said, \"That's okay, Lily. Let's go talk about Lily and see her jokes.\""
      },
      {
        "seed": 2,
        "tokens": [
          673,
          6151,
          284,
          711,
          351,
          607,
          14958,
          13,
          1375,
          1422,
          470,
          765,
          284,
          651,
          656,
          5876,
          13,
          1375,
          2227,
          284,
          467,
          284,
          262,
          3650,
          290,
          2822,
          617,
          18550,
          13,
          1375,
          1422,
          470,
          765,
          284,
          2648,
          607,
          14958,
          393,
          607,
          36062,
          13,
          198,
          198,
          29252,
          1820,
          2497,
          703,
          9247,
          20037,
          373,
          290,
          531,
          11,
          366,
          43,
          813,
          11,
          345,
          761,
          284
        ],
        "text": "Lily was scared because she loved to play with her toys. She didn't want to get into trouble. She wanted to go to the store and buy some candy. She didn't want to share her toys or her dolls.\n\nMommy saw how upset Lily was and said, \"Lily, you need to"
      },
      {
        "seed": 3,
        "tokens": [
          673,
          1807,
          607,
          5536,
          550,
          1282,
          13,
          1375,
          1816,
          284,
          262,
          3650,
          290,
          5839,
          257,
          10883,
          11569,
          13,
          1375,
          373,
          523,
          3772,
          290,
          6568,
          284,
          1949,
          340,
          13,
          1375,
          550,
          257,
          1049,
          640,
          2712,
          351,
          607,
          5536,
          11569,
          290,
          607,
          5536,
          11569,
          4120,
          287,
          262,
          5536,
          11569,
          13,
          1375,
          772,
          25889,
          290,
          665,
          49376,
          11,
          1566,
          340,
          12120,
          0,
          383
        ],
        "text": "Lily was scared because she thought her magic had come. She went to the store and bought a magical wand. She was so happy and excited to try it. She had a great time playing with her magic wand and her magic wand appeared in the magic wand. She even sang and twirled, until it disappeared! The"
      },
      {
        "seed": 4,
        "tokens": [
          673,
          1422,
          470,
          760,
          644,
          284,
          466,
          13,
          1375,
          2936,
          7926,
          290,
          3066,
          284,
          2648,
          607,
          2613,
          351,
          607,
          1545,
          11,
          5436,
          13,
          198,
          198,
          11518,
          5784,
          1015,
          20037,
          290,
          484,
          2826,
          1978,
          18177,
          1978,
          13,
          20037,
          6939,
          326,
          7373,
          607,
          2613,
          373,
          1593,
          290,
          2921,
          607,
          1545,
          257,
          1263,
          16225,
          13,
          3574,
          326,
          1110,
          319,
          11,
          20037,
          4499,
          326
        ],
        "text": "Lily was scared because she didn't know what to do. She felt sorry and decided to share her ball with her friend, Max.\n\nMax forgave Lily and they played together happily together. Lily realized that sharing her ball was important and gave her friend a big hug. From that day on, Lily learned that"
      }
    ],
    "s_dragon": [
      {
        "seed": 0,
        "tokens": [
          781,
          6320,
          607,
          12098,
          13,
          1375,
          16555,
          262,
          582,
          561,
          1282,
          351,
          607,
          13,
          1375,
          531,
          11,
          366,
          5492,
          1309,
          502,
          467,
          526,
          383,
          582,
          4838,
          465,
          2951,
          290,
          4251,
          503,
          465,
          1021,
          13,
          679,
          531,
          11,
          366,
          11380,
          11,
          475,
          307,
          10296,
          13,
          383,
          10441,
          318,
          407,
          8030,
          13,
          632,
          460,
          787,
          345,
          2121,
          526,
          198,
          198,
          464,
          10441
        ],
        "text": "The dragon roared and flapped her wings. She wished the man would come with her. She said, \"Please let me go.\" The man closed his eyes and reached out his hand. He said, \"OK, but be gentle. The dragon is not friendly. It can make you fall.\"\n\nThe dragon"
      },
      {
        "seed": 1,
        "tokens": [
          1392,
          12008,
          13,
          632,
          45615,
          290,
          4966,
          1497,
          13,
          198,
          198,
          14967,
          290,
          3409,
          547,
          3772,
          13,
          1119,
          550,
          281,
          2126,
          13,
          1119,
          1043,
          257,
          1263,
          1492,
          284,
          1100,
          13,
          1119,
          1100,
          262,
          1492,
          290,
          1043,
          257,
          1492,
          13,
          1119,
          1100,
          262,
          1492,
          1978,
          13,
          1119,
          16453,
          546,
          262,
          10441,
          13,
          1119,
          547,
          2460,
          13
        ],
        "text": "The dragon roared and got scared. It roared and ran away.\n\nTim and Sam were happy. They had an idea. They found a big book to read. They read the book and found a book. They read the book together. They forgot about the dragon. They were friends."
      },
      {
        "seed": 2,
        "tokens": [
          531,
          11,
          366,
          40,
          1101,
          257,
          21752,
          2474,
          1375,
          373,
          523,
          6568,
          11,
          673,
          1816,
          2651,
          284,
          262,
          10441,
          338,
          7002,
          13,
          383,
          10441,
          13541,
          290,
          26834,
          24829,
          13,
          198,
          198,
          464,
          10441,
          26834,
          24829,
          290,
          13112,
          1497,
          13,
          1375,
          373,
          523,
          3772,
          284,
          423,
          925,
          262,
          10441,
          2245,
          11,
          673,
          373,
          645,
          2392,
          12008,
          13,
          2735,
          673,
          373,
          1479
        ],
        "text": "The dragon roared and said, \"I'm a princess!\" She was so excited, she went forward to the dragon's journey. The dragon smiled and waved goodbye.\n\nThe dragon waved goodbye and flew away. She was so happy to have made the dragon stop, she was no longer scared. Now she was free"
      },
      {
        "seed": 3,
        "tokens": [
          4966,
          284,
          262,
          6164,
          13,
          383,
          6164,
          373,
          523,
          3772,
          13,
          679,
          550,
          1043,
          257,
          835,
          284,
          2648,
          465,
          16927,
          351,
          262,
          10441,
          338,
          1545,
          13,
          383,
          10441,
          290,
          262,
          6164,
          2627,
          262,
          1266,
          286,
          2460,
          290,
          2826,
          1978,
          1566,
          340,
          373,
          640,
          284,
          467,
          1363,
          13,
          383,
          19716,
          26280,
          262,
          10441,
          290,
          8072,
          284,
          1239,
          8711,
          757,
          13,
          383
        ],
        "text": "The dragon roared and ran to the mine. The mine was so happy. He had found a way to share his jewel with the dragon's friend. The dragon and the mine became the best of friends and played together until it was time to go home. The prince thanked the dragon and promised to never steal again. The"
      },
      {
        "seed": 4,
        "tokens": [
          13112,
          1497,
          13,
          198,
          198,
          14295,
          373,
          523,
          6507,
          13,
          679,
          2227,
          530,
          588,
          262,
          10441,
          290,
          262,
          10441,
          13,
          679,
          1807,
          326,
          262,
          10441,
          561,
          1282,
          284,
          683,
          290,
          484,
          561,
          1064,
          683,
          1978,
          13,
          198,
          198,
          2396,
          3619,
          290,
          262,
          10441,
          2067,
          284,
          2513,
          1497,
          13,
          1119,
          6807,
          290,
          1816,
          1566,
          484,
          1043,
          257,
          7932,
          1295,
          13,
          383
        ],
        "text": "The dragon roared and flew away.\n\nJack was so sad. He wanted one like the dragon and the dragon. He thought that the dragon would come to him and they would find him together.\n\nSo Jack and the dragon started to walk away. They walked and went until they found a wonderful place. The"
      }
    ],
    "s_cat_dog": [
      {
        "seed": 0,
        "tokens": [
          1807,
          340,
          373,
          8258,
          13,
          1375,
          1807,
          262,
          3797,
          561,
          711,
          351,
          607,
          290,
          262,
          3797,
          750,
          407,
          760,
          340,
          373,
          8030,
          290,
          750,
          407,
          1265,
          2687,
          329,
          1037,
          13,
          198,
          198,
          11518,
          338,
          1995,
          2497,
          262,
          3797,
          290,
          2921,
          607,
          262,
          3797,
          736,
          13,
          5436,
          373,
          407,
          3772,
          11,
          290,
          339,
          1965,
          465,
          1995,
          284,
          1037,
          683,
          13,
          2332
        ],
        "text": "The cat saw the dog and thought it was funny. She thought the cat would play with her and the cat did not know it was friendly and did not ask anyone for help.\n\nMax's mom saw the cat and gave her the cat back. Max was not happy, and he asked his mom to help him. Her"
      },
      {
        "seed": 1,
        "tokens": [
          1392,
          12008,
          13,
          1375,
          4966,
          1497,
          290,
          1364,
          4186,
          3436,
          13,
          1375,
          16896,
          290,
          3088,
          284,
          19437,
          683,
          1497,
          13,
          1375,
          3114,
          329,
          607,
          3290,
          13,
          1375,
          2497,
          257,
          1263,
          3881,
          290,
          257,
          4859,
          13,
          1375,
          13541,
          290,
          17293,
          13,
          198,
          198,
          1,
          19485,
          0,
          13707,
          0,
          13707,
          0,
          13707,
          340,
          0,
          921,
          389,
          1642,
          616,
          3290,
          8805,
          2474,
          531
        ],
        "text": "The cat saw the dog and got scared. She ran away and left Tom alone. She cried and tried to scare him away. She looked for her dog. She saw a big rock and a stick. She smiled and shouted.\n\n\"Stop! Stop! Stop! Stop it! You are making my dog mad!\" said"
      },
      {
        "seed": 2,
        "tokens": [
          3066,
          284,
          307,
          2460,
          13,
          1119,
          2826,
          1978,
          477,
          1110,
          890,
          13,
          1119,
          550,
          523,
          881,
          1257,
          13,
          843,
          262,
          3797,
          1816,
          1497,
          11,
          4305,
          262,
          2156,
          2157,
          13
        ],
        "text": "The cat saw the dog and decided to be friends. They played together all day long. They had so much fun. And the cat went away, leaving the house behind."
      },
      {
        "seed": 3,
        "tokens": [
          4966,
          284,
          340,
          13,
          383,
          3290,
          3940,
          262,
          2933,
          290,
          262,
          3290,
          13,
          383,
          3290,
          1718,
          262,
          14068,
          736,
          284,
          511,
          1363,
          13,
          198,
          198,
          43,
          813,
          290,
          5436,
          550,
          257,
          922,
          1110,
          13,
          1119,
          4499,
          326,
          2263,
          1243,
          318,
          407,
          922,
          13,
          1119,
          4499,
          326,
          617,
          1243,
          460,
          787,
          1243,
          4577,
          13
        ],
        "text": "The cat saw the dog and ran to it. The dog followed the boy and the dog. The dog took the treasure back to their home.\n\nLily and Max had a good day. They learned that taking things is not good. They learned that some things can make things easier."
      },
      {
        "seed": 4,
        "tokens": [
          4966,
          1497,
          13,
          383,
          3290,
          2227,
          284,
          711,
          13,
          198,
          198,
          1,
          19485,
          11,
          3797,
          11,
          2245,
          2474,
          262,
          3797,
          531,
          13,
          366,
          1639,
          389,
          39842,
          616,
          2613,
          0,
          13786,
          340,
          736,
          2474,
          198,
          198,
          13787,
          290,
          20037,
          547,
          12008,
          13,
          1119,
          750,
          407,
          760,
          644,
          284,
          466,
          13,
          1119,
          750,
          407,
          760,
          644,
          284,
          466,
          13,
          1119,
          750,
          407
        ],
        "text": "The cat saw the dog and ran away. The dog wanted to play.\n\n\"Stop, cat, stop!\" the cat said. \"You are ruining my ball! Give it back!\"\n\nTom and Lily were scared. They did not know what to do. They did not know what to do. They did not"
      }
    ],
    "s_sunny": [
      {
        "seed": 0,
        "tokens": [
          13,
          679,
          2497,
          262,
          5788,
          379,
          1755,
          290,
          2936,
          3772,
          13,
          679,
          9658,
          379,
          262,
          3952,
          329,
          262,
          1755,
          290,
          21256,
          329,
          262,
          1755,
          13,
          220,
          198,
          198,
          464,
          2933,
          373,
          845,
          6568,
          284,
          423,
          257,
          649,
          1545,
          13,
          679,
          1297,
          262,
          582,
          287,
          262,
          3952,
          13,
          383,
          582,
          13541,
          290,
          26834,
          736,
          13,
          220,
          198,
          198,
          1544,
          531,
          24829
        ],
        "text": "It was a sunny day. He saw the stars at night and felt happy. He stayed at the park for the night and slept for the night. \n\nThe boy was very excited to have a new friend. He told the man in the park. The man smiled and waved back. \n\nHe said goodbye"
      },
      {
        "seed": 1,
        "tokens": [
          290,
          262,
          4252,
          373,
          22751,
          13,
          383,
          6290,
          373,
          19280,
          607,
          2951,
          355,
          673,
          3114,
          503,
          262,
          4324,
          13,
          220,
          198,
          198,
          464,
          1310,
          2576,
          3940,
          262,
          4324,
          11,
          290,
          673,
          45236,
          287,
          25030,
          13,
          383,
          6290,
          373,
          523,
          1913,
          290,
          6546,
          13,
          24975,
          11,
          262,
          6290,
          2540,
          284,
          12797,
          866,
          290,
          262,
          1310,
          2576,
          2936,
          523,
          3772,
          13,
          1375
        ],
        "text": "It was a sunny day and the sun was shining. The rain was blowing her eyes as she looked out the window. \n\nThe little girl followed the window, and she gasped in awe. The rain was so strong and thick. Suddenly, the rain began to pour down and the little girl felt so happy. She"
      },
      {
        "seed": 2,
        "tokens": [
          290,
          262,
          2344,
          17948,
          832,
          262,
          6766,
          13,
          632,
          373,
          523,
          881,
          1257,
          0,
          198,
          198,
          2953,
          262,
          886,
          286,
          262,
          1110,
          11,
          5811,
          290,
          465,
          1995,
          290,
          35822,
          550,
          257,
          1049,
          640,
          379,
          262,
          3952,
          13,
          1119,
          13818,
          290,
          2826,
          1566,
          484,
          547,
          10032,
          11,
          523,
          484,
          477,
          1816,
          1363,
          290,
          484,
          547,
          3772,
          13
        ],
        "text": "It was a sunny day and the wind blew through the sky. It was so much fun!\n\nAt the end of the day, Bob and his mom and daddy had a great time at the park. They laughed and played until they were tired, so they all went home and they were happy."
      },
      {
        "seed": 3,
        "tokens": [
          290,
          484,
          1816,
          329,
          257,
          890,
          2513,
          13,
          5045,
          1820,
          373,
          4203,
          845,
          3772,
          290,
          531,
          11,
          366,
          29252,
          1820,
          11,
          460,
          356,
          467,
          319,
          262,
          1323,
          1701,
          2399,
          1995,
          1820,
          8712,
          11,
          366,
          19457,
          11,
          356,
          1183,
          467,
          1978,
          526,
          198,
          198,
          11158,
          11,
          484,
          1392,
          284,
          262,
          1323,
          2245,
          290,
          5045,
          1820,
          1392,
          319,
          262,
          1323,
          13,
          383
        ],
        "text": "It was a sunny day and they went for a long walk. Timmy was feeling very happy and said, \"Mommy, can we go on the bus?\" His mommy replied, \"Sure, we'll go together.\"\n\nFinally, they got to the bus stop and Timmy got on the bus. The"
      },
      {
        "seed": 4,
        "tokens": [
          13,
          1119,
          1111,
          13541,
          13,
          1119,
          1816,
          2354,
          284,
          711,
          290,
          550,
          6041,
          286,
          1257,
          13,
          5045,
          373,
          3772,
          1165,
          13,
          1119,
          547,
          1266,
          2460,
          13
        ],
        "text": "It was a sunny day. They both smiled. They went outside to play and had lots of fun. Tim was happy too. They were best friends."
      }
    ],
    "p_dialogue": [
      {
        "seed": 0,
        "tokens": [
          198,
          1,
          13300,
          340,
          338,
          3621,
          13,
          775,
          655,
          423,
          284,
          307,
          23507,
          290,
          23507,
          13,
          775,
          460,
          804,
          379,
          345,
          422,
          994,
          526,
          198,
          198,
          14967,
          290,
          20037,
          4251,
          503,
          511,
          2832,
          290,
          12615,
          13,
          1119,
          531,
          11,
          366,
          1026,
          338,
          3621,
          13,
          3914,
          338,
          1949,
          340,
          13,
          632,
          338,
          3608,
          13,
          2141,
          345,
          765,
          284,
          1949,
          340,
          1701
        ],
        "text": "He said, \n\"Maybe it's nice. We just have to be polite and polite. We can look at you from here.\"\n\nTim and Lily reached out their hands and touched. They said, \"It's nice. Let's try it. It's cool. Do you want to try it?\""
      },
      {
        "seed": 1,
        "tokens": [
          198,
          464,
          582,
          3114,
          379,
          465,
          1021,
          290,
          13541,
          13,
          679,
          531,
          11,
          366,
          1639,
          389,
          845,
          1611,
          526,
          220,
          198,
          464,
          2933,
          13541,
          290,
          14464,
          13,
          679,
          373,
          9675,
          326,
          339,
          373,
          1498,
          284,
          307,
          257,
          14431,
          1048,
          13
        ],
        "text": "He said, \nThe man looked at his hand and smiled. He said, \"You are very kind.\" \nThe boy smiled and nodded. He was glad that he was able to be a generous person."
      },
      {
        "seed": 2,
        "tokens": [
          198,
          1,
          5812,
          645,
          40754,
          262,
          21264,
          8712,
          11,
          366,
          3987,
          470,
          5490,
          11,
          314,
          1839,
          470,
          5938,
          345,
          2474,
          198,
          464,
          21264,
          13541,
          290,
          531,
          11,
          366,
          18690,
          11,
          314,
          1839,
          470,
          5938,
          345,
          11,
          314,
          1839,
          470,
          5938,
          345,
          1911,
          198,
          464,
          21264,
          373,
          523,
          3772,
          13,
          679,
          531,
          11,
          366,
          1639,
          821,
          7062,
          13,
          2735,
          345,
          460
        ],
        "text": "He said, \n\"Oh no!\", the frog replied, \"Don't worry, I won't hurt you!\"\nThe frog smiled and said, \"Ok, I won't hurt you, I won't hurt you\".\nThe frog was so happy. He said, \"You're welcome. Now you can"
      },
      {
        "seed": 3,
        "tokens": [
          198,
          1,
          5297,
          11,
          345,
          821,
          13,
          887,
          717,
          11,
          345,
          423,
          284,
          2648,
          534,
          2119,
          553,
          24799,
          531,
          11,
          2111,
          284,
          3151,
          262,
          1353,
          286,
          262,
          10580,
          13,
          22162,
          750,
          262,
          976,
          329,
          607,
          3956,
          290,
          484,
          1111,
          13818,
          13,
          220,
          198,
          464,
          5268,
          13
        ],
        "text": "He said, \n\"Yes, you're. But first, you have to share your room,\" Sara said, trying to reach the top of the tower. Lucy did the same for her brother and they both laughed. \nThe End."
      },
      {
        "seed": 4,
        "tokens": [
          198,
          1,
          40,
          1842,
          345,
          11,
          5045,
          13,
          921,
          389,
          262,
          1266,
          1995,
          1683,
          2474
        ],
        "text": "He said, \n\"I love you, Tim. You are the best mom ever!\""
      }
    ],
    "p_past": [
      {
        "seed": 0,
        "tokens": [
          198,
          1,
          6090,
          314,
          2652,
          379,
          534,
          10955,
          1701,
          1965,
          262,
          2576,
          13,
          198,
          198,
          464,
          2933,
          13541,
          290,
          531,
          11,
          366,
          2949,
          11,
          314,
          481,
          2652,
          290,
          3993,
          13,
          11391,
          481,
          307,
          23036,
          526,
          198,
          198,
          2396,
          262,
          2576,
          1816,
          284,
          607,
          2156,
          290,
          607,
          1995,
          2921,
          607,
          257,
          1263,
          16225,
          13,
          1375,
          27946,
          607,
          922,
          3847,
          290,
          1816
        ],
        "text": "Yesterday, the boy \n\"Can I stay at your birthday?\" asked the girl.\n\nThe boy smiled and said, \"No, I will stay and sleep. Everything will be alright.\"\n\nSo the girl went to her house and her mom gave her a big hug. She kissed her goodnight and went"
      },
      {
        "seed": 1,
        "tokens": [
          198,
          464,
          2933,
          373,
          523,
          6568,
          339,
          11687,
          1088,
          262,
          2156,
          11,
          25849,
          284,
          262,
          9234,
          13,
          383,
          9234,
          373,
          523,
          3772,
          326,
          339,
          2067,
          14376,
          13,
          198,
          198,
          464,
          2933,
          13541,
          290,
          531,
          11,
          366,
          40,
          588,
          534,
          1468,
          2156,
          11,
          314,
          892,
          345,
          460,
          2652,
          351,
          502,
          526,
          220,
          198,
          464,
          2933,
          373,
          523,
          10607,
          13,
          679,
          531
        ],
        "text": "Yesterday, the boy \nThe boy was so excited he jumped around the house, waving to the monster. The monster was so happy that he started laughing.\n\nThe boy smiled and said, \"I like your old house, I think you can stay with me.\" \nThe boy was so pleased. He said"
      },
      {
        "seed": 2,
        "tokens": [
          198,
          1,
          5812,
          645,
          40754,
          531,
          11254,
          1820,
          11,
          366,
          16773,
          351,
          502,
          526,
          198,
          198,
          464,
          2933,
          11687,
          290,
          11687,
          13,
          679,
          4966,
          1613,
          465,
          1995,
          290,
          531,
          11,
          366,
          29252,
          1820,
          11,
          460,
          314,
          6594,
          262,
          17026,
          1701,
          198,
          198,
          29252,
          1820,
          13541,
          290,
          531,
          11,
          366,
          5297,
          11,
          1310,
          2933,
          11,
          1309,
          338,
          1011,
          257,
          6594,
          1978
        ],
        "text": "Yesterday, the boy \n\"Oh no!\", said Mommy, \"Come with me.\"\n\nThe boy jumped and jumped. He ran past his mom and said, \"Mommy, can I ride the bicycle?\"\n\nMommy smiled and said, \"Yes, little boy, let's take a ride together"
      },
      {
        "seed": 3,
        "tokens": [
          198,
          1,
          2061,
          389,
          345,
          1804,
          994,
          1701,
          1965,
          262,
          1995,
          13,
          198,
          198,
          464,
          2576,
          13541,
          13,
          366,
          40,
          1101,
          18682,
          616,
          1097,
          2474,
          673,
          531,
          13,
          198,
          198,
          464,
          1995,
          13541,
          13,
          366,
          5756,
          338,
          651,
          257,
          649,
          4572,
          329,
          8073,
          9975,
          526,
          198,
          198,
          464,
          2576,
          4193,
          262,
          2576,
          4259,
          262,
          1097,
          13,
          632,
          2921,
          607,
          257
        ],
        "text": "Yesterday, the boy \n\"What are you doing here?\" asked the mom.\n\nThe girl smiled. \"I'm fixing my car!\" she said.\n\nThe mom smiled. \"Let's get a new machine for dinner tonight.\"\n\nThe girl helped the girl fix the car. It gave her a"
      },
      {
        "seed": 4,
        "tokens": [
          198,
          2215,
          339,
          5284,
          11,
          262,
          2156,
          373,
          845,
          37438,
          290,
          845,
          43044,
          13,
          1550,
          262,
          33179,
          11,
          339,
          2497,
          734,
          1115,
          2460,
          13,
          1119,
          547,
          477,
          2712,
          1978,
          290,
          2491,
          1088,
          262,
          2156,
          13,
          198,
          198,
          464,
          2933,
          290,
          465,
          2460,
          2826,
          287,
          262,
          11376,
          477,
          6672,
          13,
          1119,
          13818,
          290,
          550,
          6041,
          286,
          1257,
          13,
          3244,
          484,
          547
        ],
        "text": "Yesterday, the boy \nWhen he arrived, the house was very cozy and very tidy. On the porch, he saw two three friends. They were all playing together and running around the house.\n\nThe boy and his friends played in the garden all afternoon. They laughed and had lots of fun. Then they were"
      }
    ],
    "p_plural": [
      {
        "seed": 0,
        "tokens": [
          198,
          198,
          1,
          1026,
          338,
          3621,
          13,
          775,
          389,
          3772,
          345,
          423,
          257,
          922,
          1545,
          13,
          775,
          460,
          2648,
          290,
          711,
          1978,
          553,
          3932,
          531,
          13,
          198,
          198,
          29252,
          13541,
          13,
          1375,
          373,
          6613,
          286,
          606,
          13,
          198,
          198,
          1,
          2504,
          338,
          7932,
          13,
          3914,
          338,
          2648,
          290,
          1011,
          4962,
          13,
          1320,
          835,
          11,
          356,
          460,
          307,
          2460,
          553,
          673
        ],
        "text": "There were two \n\n\"It's nice. We are happy you have a good friend. We can share and play together,\" Ben said.\n\nMom smiled. She was proud of them.\n\n\"That's wonderful. Let's share and take turns. That way, we can be friends,\" she"
      },
      {
        "seed": 1,
        "tokens": [
          17479,
          290,
          607,
          1995,
          13818,
          13,
          1119,
          2936,
          3772,
          13
        ],
        "text": "There were two icky and her mom laughed. They felt happy."
      },
      {
        "seed": 2,
        "tokens": [
          198,
          198,
          40797,
          373,
          523,
          3772,
          284,
          2193,
          1223,
          649,
          13,
          2080,
          607,
          649,
          21613,
          11,
          673,
          373,
          1498,
          284,
          787,
          607,
          845,
          3772,
          290,
          3772,
          13
        ],
        "text": "There were two \n\nAmy was so happy to learn something new. With her new pencil, she was able to make her very happy and happy."
      },
      {
        "seed": 3,
        "tokens": [
          198,
          1,
          1135,
          750,
          11,
          4186,
          13,
          775,
          655,
          2227,
          284,
          910,
          7926,
          284,
          11254,
          13,
          11254,
          481,
          307,
          8805,
          13,
          921,
          815,
          307,
          3772,
          284,
          1949,
          649,
          1243,
          13,
          2141,
          345,
          1833,
          1701,
          673,
          1965,
          13,
          198,
          198,
          13787,
          14464,
          13,
          679,
          8288,
          284,
          1037,
          465,
          2460,
          290,
          787,
          649,
          1243,
          13,
          679,
          5784,
          1015,
          606,
          290,
          531,
          11
        ],
        "text": "There were two \n\"We did, Tom. We just wanted to say sorry to Mom. Mom will be mad. You should be happy to try new things. Do you understand?\" she asked.\n\nTom nodded. He liked to help his friends and make new things. He forgave them and said,"
      },
      {
        "seed": 4,
        "tokens": [
          198,
          50,
          10757,
          373,
          3492,
          284,
          7301,
          13,
          1375,
          2936,
          523,
          6568,
          530,
          1110,
          13,
          1375,
          13541,
          290,
          4966,
          503,
          284,
          7301,
          649,
          4113,
          13,
          220,
          198,
          198,
          2953,
          262,
          886,
          286,
          262,
          1110,
          11,
          17581,
          1816,
          736,
          284,
          607,
          2119,
          13,
          1375,
          2936,
          845,
          3772,
          290,
          6568,
          13,
          1375,
          373,
          645,
          2392,
          42537,
          13,
          220,
          198,
          198,
          50,
          10757
        ],
        "text": "There were two \nSandy was ready to explore. She felt so excited one day. She smiled and ran out to explore new places. \n\nAt the end of the day, Sandy went back to her room. She felt very happy and excited. She was no longer restless. \n\nSandy"
      }
    ],
    "p_descriptor": [
      {
        "seed": 0,
        "tokens": [
          198,
          1,
          13300,
          340,
          318,
          3621,
          553,
          10490,
          531,
          13,
          220,
          198,
          3347,
          17157,
          866,
          422,
          262,
          3881,
          1978,
          290,
          484,
          2826,
          1978,
          13,
          220,
          198,
          29284,
          550,
          523,
          881,
          1257,
          326,
          673,
          2227,
          284,
          6594,
          262,
          3881,
          13,
          1375,
          550,
          262,
          1266,
          1110,
          1683,
          0,
          220,
          198,
          2953,
          262,
          886,
          286,
          262,
          1110,
          11,
          484,
          550,
          1263,
          21845,
          319
        ],
        "text": "The big red \n\"Maybe it is nice,\" Sarah said. \nShe bent down from the rock together and they played together. \nSarah had so much fun that she wanted to ride the rock. She had the best day ever! \nAt the end of the day, they had big smiles on"
      },
      {
        "seed": 1,
        "tokens": [
          198,
          464,
          582,
          3114,
          379,
          465,
          1021,
          290,
          13541,
          13,
          679,
          373,
          523,
          3772,
          284,
          423,
          884,
          257,
          2041,
          6979,
          422,
          262,
          5509,
          13,
          679,
          26834,
          24829,
          284,
          262,
          5509,
          290,
          18177,
          4966,
          736,
          284,
          465,
          2156,
          13
        ],
        "text": "The big red \nThe man looked at his hand and smiled. He was so happy to have such a special gift from the tree. He waved goodbye to the tree and happily ran back to his house."
      },
      {
        "seed": 2,
        "tokens": [
          198,
          198,
          464,
          1310,
          2576,
          13818,
          290,
          262,
          1310,
          2576,
          373,
          523,
          3772,
          326,
          673,
          550,
          4193,
          262,
          1310,
          530,
          13
        ],
        "text": "The big red \n\nThe little girl laughed and the little girl was so happy that she had helped the little one."
      },
      {
        "seed": 3,
        "tokens": [
          198,
          1,
          8241,
          389,
          345,
          11,
          1545,
          1701,
          5045,
          1820,
          1965,
          13,
          198,
          198,
          1,
          40,
          1101,
          24799,
          553,
          24799,
          531,
          13,
          366,
          40,
          1101,
          257,
          1310,
          12008,
          286,
          345,
          13,
          921,
          460,
          470,
          5594,
          994,
          290,
          345,
          460,
          470,
          5594,
          284,
          502,
          526,
          198,
          198,
          50,
          3301,
          290,
          5045,
          1820,
          1111,
          2936,
          7926,
          11,
          475,
          484,
          1422,
          470,
          760
        ],
        "text": "The big red \n\"Who are you, friend?\" Timmy asked.\n\n\"I'm Sara,\" Sara said. \"I'm a little scared of you. You can't belong here and you can't belong to me.\"\n\nSara and Timmy both felt sorry, but they didn't know"
      },
      {
        "seed": 4,
        "tokens": [
          198,
          198,
          18861,
          13541,
          13,
          366,
          1639,
          1043,
          340,
          13,
          2735,
          314,
          423,
          1576,
          329,
          345,
          284,
          467,
          284,
          262,
          3952,
          2474,
          198,
          198,
          18861,
          26280,
          465,
          1545,
          290,
          4966,
          503,
          284,
          262,
          26728,
          13,
          679,
          550,
          257,
          1049,
          640,
          25635,
          736,
          290,
          6071,
          13,
          679,
          373,
          845,
          6568,
          284,
          307,
          2354,
          290,
          766,
          477,
          262,
          7932,
          1243,
          339,
          714
        ],
        "text": "The big red \n\nBob smiled. \"You found it. Now I have enough for you to go to the park!\"\n\nBob thanked his friend and ran out to the swings. He had a great time swinging back and forth. He was very excited to be outside and see all the wonderful things he could"
      }
    ],
    "p_named": [
      {
        "seed": 0,
        "tokens": [
          2883,
          511,
          640,
          379,
          19613,
          13,
          1119,
          711,
          287,
          262,
          3952,
          351,
          511,
          1995,
          13,
          1119,
          423,
          1257,
          1978,
          13,
          1119,
          389,
          3772,
          13
        ],
        "text": "Lily and the cat  enjoy their time at noon. They play in the park with their mom. They have fun together. They are happy."
      },
      {
        "seed": 1,
        "tokens": [
          17479,
          290,
          607,
          1995,
          13,
          1119,
          13818,
          290,
          550,
          1257,
          13,
          20037,
          16453,
          284,
          910,
          24829,
          284,
          262,
          3797,
          290,
          607,
          1995,
          13,
          1119,
          1364,
          262,
          2156,
          290,
          1816,
          284,
          511,
          2119,
          13,
          20037,
          550,
          257,
          2089,
          4320,
          13,
          1375,
          27947,
          286,
          2712,
          351,
          607,
          14958,
          290,
          607,
          1995,
          290,
          9955,
          13,
          1375,
          27947,
          286,
          852,
          257,
          3797,
          508,
          8288
        ],
        "text": "Lily and the cat icky and her mom. They laughed and had fun. Lily forgot to say goodbye to the cat and her mom. They left the house and went to their room. Lily had a bad dream. She dreamed of playing with her toys and her mom and dad. She dreamed of being a cat who liked"
      },
      {
        "seed": 2,
        "tokens": [
          2826,
          1978,
          329,
          257,
          981,
          11,
          475,
          262,
          4870,
          1422,
          470,
          765,
          284,
          1577,
          510,
          780,
          484,
          1422,
          470,
          765,
          284,
          1577,
          510,
          511,
          14958,
          13,
          1375,
          2993,
          607,
          3956,
          290,
          673,
          3636,
          470,
          423,
          284,
          1577,
          510,
          13,
          1375,
          1422,
          470,
          765,
          284,
          1577,
          510,
          13,
          220,
          198,
          198,
          1,
          5492,
          11,
          1309,
          502,
          711,
          351,
          534,
          14958,
          553
        ],
        "text": "Lily and the cat  played together for a while, but the owner didn't want to give up because they didn't want to give up their toys. She knew her brother and she wouldn't have to give up. She didn't want to give up. \n\n\"Please, let me play with your toys,\""
      },
      {
        "seed": 3,
        "tokens": [
          198,
          1,
          8241,
          389,
          345,
          11,
          3797,
          1701,
          5045,
          1820,
          1965,
          13,
          198,
          198,
          1,
          40,
          1101,
          24799,
          553,
          20037,
          531,
          13,
          366,
          40,
          1101,
          257,
          1310,
          3797,
          13,
          1867,
          338,
          534,
          1438,
          1701,
          198,
          198,
          1,
          40,
          1101,
          20037,
          553,
          5045,
          8712,
          13,
          366,
          40,
          1101,
          257,
          1310,
          3797,
          11,
          290,
          428,
          318,
          257,
          3621,
          1438,
          329,
          345,
          13
        ],
        "text": "Lily and the cat \n\"Who are you, cat?\" Timmy asked.\n\n\"I'm Sara,\" Lily said. \"I'm a little cat. What's your name?\"\n\n\"I'm Lily,\" Tim replied. \"I'm a little cat, and this is a nice name for you."
      },
      {
        "seed": 4,
        "tokens": [
          198,
          1,
          2061,
          389,
          345,
          1804,
          1701,
          11254,
          1139,
          13,
          366,
          1639,
          423,
          1576,
          2057,
          329,
          23084,
          13,
          921,
          460,
          423,
          23084,
          783,
          13,
          1374,
          546,
          428,
          1701,
          198,
          198,
          43,
          813,
          290,
          15899,
          8212,
          13,
          1119,
          1842,
          23084,
          13,
          198,
          198,
          1,
          2949,
          11,
          645,
          11,
          645,
          23084,
          2474,
          3932,
          1139,
          13,
          366,
          1212,
          318,
          616,
          23084,
          13,
          921
        ],
        "text": "Lily and the cat \n\"What are you doing?\" Mom says. \"You have enough food for dessert. You can have dessert now. How about this?\"\n\nLily and Spot smile. They love dessert.\n\n\"No, no, no dessert!\" Ben says. \"This is my dessert. You"
      }
    ]
  },
  "top_5_next": [
    {
      "position": 0,
      "context_token": "Once",
      "top_5": [
        {
          "token": " upon",
          "prob": 0.82993
        },
        {
          "token": " there",
          "prob": 0.105514
        },
        {
          "token": ",",
          "prob": 0.011121
        },
        {
          "token": " he",
          "prob": 0.006337
        },
        {
          "token": " a",
          "prob": 0.004935
        }
      ]
    },
    {
      "position": 1,
      "context_token": " upon",
      "top_5": [
        {
          "token": " a",
          "prob": 0.985656
        },
        {
          "token": " an",
          "prob": 0.003137
        },
        {
          "token": " there",
          "prob": 0.002443
        },
        {
          "token": " the",
          "prob": 0.000722
        },
        {
          "token": " one",
          "prob": 0.000496
        }
      ]
    },
    {
      "position": 2,
      "context_token": " a",
      "top_5": [
        {
          "token": " time",
          "prob": 0.999196
        },
        {
          "token": " way",
          "prob": 0.000131
        },
        {
          "token": " day",
          "prob": 9.9e-05
        },
        {
          "token": " long",
          "prob": 8.5e-05
        },
        {
          "token": " week",
          "prob": 3.6e-05
        }
      ]
    },
    {
      "position": 3,
      "context_token": " time",
      "top_5": [
        {
          "token": ",",
          "prob": 0.852672
        },
        {
          "token": " there",
          "prob": 0.139195
        },
        {
          "token": " upon",
          "prob": 0.001282
        },
        {
          "token": " in",
          "prob": 0.00103
        },
        {
          "token": " a",
          "prob": 0.000802
        }
      ]
    },
    {
      "position": 4,
      "context_token": ",",
      "top_5": [
        {
          "token": " there",
          "prob": 0.963621
        },
        {
          "token": " a",
          "prob": 0.010705
        },
        {
          "token": " in",
          "prob": 0.010056
        },
        {
          "token": " two",
          "prob": 0.002973
        },
        {
          "token": " it",
          "prob": 0.001027
        }
      ]
    },
    {
      "position": 5,
      "context_token": " there",
      "top_5": [
        {
          "token": " was",
          "prob": 0.899303
        },
        {
          "token": " were",
          "prob": 0.065145
        },
        {
          "token": " lived",
          "prob": 0.03487
        },
        {
          "token": " is",
          "prob": 0.000134
        },
        {
          "token": " are",
          "prob": 7.2e-05
        }
      ]
    },
    {
      "position": 6,
      "context_token": " was",
      "top_5": [
        {
          "token": " a",
          "prob": 0.963476
        },
        {
          "token": " an",
          "prob": 0.035095
        },
        {
          "token": " two",
          "prob": 0.000355
        },
        {
          "token": " the",
          "prob": 0.000215
        },
        {
          "token": " one",
          "prob": 8.7e-05
        }
      ]
    },
    {
      "position": 7,
      "context_token": " a",
      "top_5": [
        {
          "token": " little",
          "prob": 0.303382
        },
        {
          "token": " boy",
          "prob": 0.05272
        },
        {
          "token": " big",
          "prob": 0.042362
        },
        {
          "token": " girl",
          "prob": 0.029115
        },
        {
          "token": " happy",
          "prob": 0.021301
        }
      ]
    }
  ],
  "weight_stats": {
    "embedding_norm": 626.6326,
    "output_embedding_norm": 626.6326,
    "layer_norms": [
      {
        "layer": 0,
        "qkv_norm": 17.5554,
        "attn_out_norm": 7.801,
        "ffn_up_norm": 24.2334,
        "ffn_down_norm": 23.9651
      },
      {
        "layer": 1,
        "qkv_norm": 21.123,
        "attn_out_norm": 10.93,
        "ffn_up_norm": 26.9946,
        "ffn_down_norm": 24.0909
      },
      {
        "layer": 2,
        "qkv_norm": 22.4304,
        "attn_out_norm": 11.0491,
        "ffn_up_norm": 28.0359,
        "ffn_down_norm": 25.3545
      },
      {
        "layer": 3,
        "qkv_norm": 21.238,
        "attn_out_norm": 11.4391,
        "ffn_up_norm": 28.7493,
        "ffn_down_norm": 26.6404
      },
      {
        "layer": 4,
        "qkv_norm": 21.7779,
        "attn_out_norm": 11.5236,
        "ffn_up_norm": 29.0673,
        "ffn_down_norm": 27.2758
      },
      {
        "layer": 5,
        "qkv_norm": 23.374,
        "attn_out_norm": 14.1892,
        "ffn_up_norm": 28.9889,
        "ffn_down_norm": 27.8154
      }
    ],
    "embedding_top5_singular_values": [
      621.7134,
      37.631,
      18.8921,
      10.6424,
      8.7161
    ],
    "attention_logit_mean_per_layer": [
      -0.7704,
      -1.8483,
      -0.096,
      0.3447,
      -1.0547,
      1.2159
    ],
    "attention_logit_std_per_layer": [
      1.1793,
      2.8523,
      2.9643,
      1.8489,
      1.8686,
      2.093
    ]
  },
  "probe_results": {
    "uses_quotation_marks": 1.0,
    "past_tense_after_yesterday": 0.4,
    "plural_after_two": 0.2,
    "coherent_three_word_phrase": 0.0,
    "multi_sentence": 1.0,
    "consistent_named_entity": 0.8,
    "vocabulary_size": 495,
    "loss_below_threshold": true
  }
}